whisper_speaker_emotion/__init__.py
whisper_speaker_emotion/core.py
whisper_speaker_emotion-0.1.0.dist-info/licenses/LICENSE
whisper_speaker_emotion-0.1.0.dist-info/METADATA
whisper_speaker_emotion-0.1.0.dist-info/WHEEL
whisper_speaker_emotion-0.1.0.dist-info/top_level.txt
whisper_speaker_emotion-0.1.0.dist-info/RECORD
