Metadata-Version: 2.4
Name: whisper-speaker-emotion
Version: 0.1.0
Summary: Emotion-aware speaker tone analysis using pitch and RMS from Whisper diarized VTT with timestamps
Author: Ashwin B
License-Expression: MIT
Requires-Python: >=3.9
License-File: LICENSE
Requires-Dist: numpy
Requires-Dist: pandas
Requires-Dist: scipy
Requires-Dist: librosa
Dynamic: license-file
